numba_celltree/__init__.py
numba_celltree/cast.py
numba_celltree/celltree.py
numba_celltree/celltree_base.py
numba_celltree/constants.py
numba_celltree/creation.py
numba_celltree/demo.py
numba_celltree/edge_celltree.py
numba_celltree/geometry_utils.py
numba_celltree/query.py
numba_celltree/utils.py
numba_celltree/algorithms/__init__.py
numba_celltree/algorithms/barycentric_triangle.py
numba_celltree/algorithms/barycentric_wachspress.py
numba_celltree/algorithms/cohen_sutherland.py
numba_celltree/algorithms/cyrus_beck.py
numba_celltree/algorithms/liang_barsky.py
numba_celltree/algorithms/separating_axis.py
numba_celltree/algorithms/sutherland_hodgman.py
numba_celltree-0.4.1.dist-info/METADATA
numba_celltree-0.4.1.dist-info/WHEEL
numba_celltree-0.4.1.dist-info/licenses/LICENSE
numba_celltree-0.4.1.dist-info/RECORD
