Metadata-Version: 2.4
Name: numba_celltree
Version: 0.4.1
Summary: Cell Tree Spatial Index
Project-URL: Home, https://github.com/deltares/numba_celltree
Project-URL: Code, https://github.com/deltares/numba_celltree
Project-URL: Issues, https://github.com/deltares/numba_celltree/issues
Maintainer-email: Huite Bootsma <huite.bootsma@deltares.nl>
License: MIT
License-File: LICENSE
Keywords: mesh,spatial index,ugrid,unstructured grid
Classifier: Development Status :: 4 - Beta
Classifier: Intended Audience :: Science/Research
Classifier: License :: OSI Approved :: MIT License
Classifier: Operating System :: OS Independent
Classifier: Programming Language :: Python
Classifier: Programming Language :: Python :: 3
Classifier: Programming Language :: Python :: 3.9
Classifier: Programming Language :: Python :: 3.10
Classifier: Programming Language :: Python :: 3.11
Classifier: Programming Language :: Python :: 3.12
Classifier: Programming Language :: Python :: 3.13
Classifier: Programming Language :: Python :: Implementation :: CPython
Classifier: Topic :: Scientific/Engineering
Requires-Python: >=3.9
Requires-Dist: numba
Requires-Dist: numpy
Provides-Extra: all
Requires-Dist: matplotlib; extra == 'all'
Provides-Extra: docs
Requires-Dist: matplotlib; extra == 'docs'
Requires-Dist: pydata-sphinx-theme; extra == 'docs'
Requires-Dist: sphinx; extra == 'docs'
Requires-Dist: sphinx-gallery; extra == 'docs'
